setup.py
etsy/__init__.py
etsy/_core.py
etsy/_multipartformdataencode.py
etsy/_v2.py
etsy/etsy_env.py
etsy/oauth.py
etsy/test_v2.py
etsy.egg-info/PKG-INFO
etsy.egg-info/SOURCES.txt
etsy.egg-info/dependency_links.txt
etsy.egg-info/requires.txt
etsy.egg-info/top_level.txt
test/test_core.py