Metadata-Version: 1.0
Name: etsy
Version: 0.3
Summary: Python access to the Etsy API
Home-page: UNKNOWN
Author: Dan McKinley
Author-email: dan@etsy.com
License: GPL v3
Keywords: etsy api handmade
Platform: UNKNOWN
